Workbook

Sheet P&L Dashboard
A1: Campaign Profitability Dashboard — 6-Month View (Feb–Jul 2026)
A2: Every cell is a live SUMIF against CostData & Production. Change any cost and the P&L updates.
A4: Total Cost | C4: Total Revenue | E4: Gross Profit | G4: Blended Margin | I4: Total FTE | K4: Cost / Sale
A5: =CostData!J77 | C5: =Production!F77 | E5: =Production!F77-CostData!J77 | G5: =(Production!F77-CostData!J77)/Production!F77 | I5: =CostData!C77/6 | K5: =CostData!J77/Production!D77
A8: Rank | B8: Campaign | C8: Type | D8: Total Cost | E8: Revenue | F8: Gross Profit | G8: Margin % | H8: Cost/Contact | I8: Cost/Sale | J8: Rev/FTE | K8: ROI
A9: =RANK(F9,$F$9:$F$20) | B9: Vodacom Upgrades | C9: Sales | D9: =SUMIF(CostData!$A$5:$A$76,B9,CostData!$J$5:$J$76) | E9: =SUMIF(Production!$A$5:$A$76,B9,Production!$F$5:$F$76) | F9: =E9-D9 | G9: =F9/E9 | H9: =D9/SUMIF(Production!$A$5:$A$76,B9,Production!$C$5:$C$76) | I9: =D9/SUMIF(Production!$A$5:$A$76,B9,Production!$D$5:$D$76) | J9: =E9/(SUMIF(CostData!$A$5:$A$76,B9,CostData!$C$5:$C$76)/6) | K9: =F9/D9
A10: =RANK(F10,$F$9:$F$20) | B10: ABSA Collections | C10: Collections | D10: =SUMIF(CostData!$A$5:$A$76,B10,CostData!$J$5:$J$76) | E10: =SUMIF(Production!$A$5:$A$76,B10,Production!$F$5:$F$76) | F10: =E10-D10 | G10: =F10/E10 | H10: =D10/SUMIF(Production!$A$5:$A$76,B10,Production!$C$5:$C$76) | I10: =D10/SUMIF(Production!$A$5:$A$76,B10,Production!$D$5:$D$76) | J10: =E10/(SUMIF(CostData!$A$5:$A$76,B10,CostData!$C$5:$C$76)/6) | K10: =F10/D10
A11: =RANK(F11,$F$9:$F$20) | B11: MTN Retentions | C11: Retentions | D11: =SUMIF(CostData!$A$5:$A$76,B11,CostData!$J$5:$J$76) | E11: =SUMIF(Production!$A$5:$A$76,B11,Production!$F$5:$F$76) | F11: =E11-D11 | G11: =F11/E11 | H11: =D11/SUMIF(Production!$A$5:$A$76,B11,Production!$C$5:$C$76) | I11: =D11/SUMIF(Production!$A$5:$A$76,B11,Production!$D$5:$D$76) | J11: =E11/(SUMIF(CostData!$A$5:$A$76,B11,CostData!$C$5:$C$76)/6) | K11: =F11/D11
A12: =RANK(F12,$F$9:$F$20) | B12: Takealot Care | C12: Customer Care | D12: =SUMIF(CostData!$A$5:$A$76,B12,CostData!$J$5:$J$76) | E12: =SUMIF(Production!$A$5:$A$76,B12,Production!$F$5:$F$76) | F12: =E12-D12 | G12: =F12/E12 | H12: =D12/SUMIF(Production!$A$5:$A$76,B12,Production!$C$5:$C$76) | I12: =D12/SUMIF(Production!$A$5:$A$76,B12,Production!$D$5:$D$76) | J12: =E12/(SUMIF(CostData!$A$5:$A$76,B12,CostData!$C$5:$C$76)/6) | K12: =F12/D12
A13: =RANK(F13,$F$9:$F$20) | B13: Telkom Tech Support | C13: Tech Support | D13: =SUMIF(CostData!$A$5:$A$76,B13,CostData!$J$5:$J$76) | E13: =SUMIF(Production!$A$5:$A$76,B13,Production!$F$5:$F$76) | F13: =E13-D13 | G13: =F13/E13 | H13: =D13/SUMIF(Production!$A$5:$A$76,B13,Production!$C$5:$C$76) | I13: =D13/SUMIF(Production!$A$5:$A$76,B13,Production!$D$5:$D$76) | J13: =E13/(SUMIF(CostData!$A$5:$A$76,B13,CostData!$C$5:$C$76)/6) | K13: =F13/D13
A14: =RANK(F14,$F$9:$F$20) | B14: Nedbank Debt Review | C14: Collections | D14: =SUMIF(CostData!$A$5:$A$76,B14,CostData!$J$5:$J$76) | E14: =SUMIF(Production!$A$5:$A$76,B14,Production!$F$5:$F$76) | F14: =E14-D14 | G14: =F14/E14 | H14: =D14/SUMIF(Production!$A$5:$A$76,B14,Production!$C$5:$C$76) | I14: =D14/SUMIF(Production!$A$5:$A$76,B14,Production!$D$5:$D$76) | J14: =E14/(SUMIF(CostData!$A$5:$A$76,B14,CostData!$C$5:$C$76)/6) | K14: =F14/D14
A15: =RANK(F15,$F$9:$F$20) | B15: DStv Upsell | C15: Sales | D15: =SUMIF(CostData!$A$5:$A$76,B15,CostData!$J$5:$J$76) | E15: =SUMIF(Production!$A$5:$A$76,B15,Production!$F$5:$F$76) | F15: =E15-D15 | G15: =F15/E15 | H15: =D15/SUMIF(Production!$A$5:$A$76,B15,Production!$C$5:$C$76) | I15: =D15/SUMIF(Production!$A$5:$A$76,B15,Production!$D$5:$D$76) | J15: =E15/(SUMIF(CostData!$A$5:$A$76,B15,CostData!$C$5:$C$76)/6) | K15: =F15/D15
A16: =RANK(F16,$F$9:$F$20) | B16: Discovery Lead Gen | C16: Lead Gen | D16: =SUMIF(CostData!$A$5:$A$76,B16,CostData!$J$5:$J$76) | E16: =SUMIF(Production!$A$5:$A$76,B16,Production!$F$5:$F$76) | F16: =E16-D16 | G16: =F16/E16 | H16: =D16/SUMIF(Production!$A$5:$A$76,B16,Production!$C$5:$C$76) | I16: =D16/SUMIF(Production!$A$5:$A$76,B16,Production!$D$5:$D$76) | J16: =E16/(SUMIF(CostData!$A$5:$A$76,B16,CostData!$C$5:$C$76)/6) | K16: =F16/D16
A17: =RANK(F17,$F$9:$F$20) | B17: Cell C Winback | C17: Retentions | D17: =SUMIF(CostData!$A$5:$A$76,B17,CostData!$J$5:$J$76) | E17: =SUMIF(Production!$A$5:$A$76,B17,Production!$F$5:$F$76) | F17: =E17-D17 | G17: =F17/E17 | H17: =D17/SUMIF(Production!$A$5:$A$76,B17,Production!$C$5:$C$76) | I17: =D17/SUMIF(Production!$A$5:$A$76,B17,Production!$D$5:$D$76) | J17: =E17/(SUMIF(CostData!$A$5:$A$76,B17,CostData!$C$5:$C$76)/6) | K17: =F17/D17
A18: =RANK(F18,$F$9:$F$20) | B18: OUTsurance Sales | C18: Sales | D18: =SUMIF(CostData!$A$5:$A$76,B18,CostData!$J$5:$J$76) | E18: =SUMIF(Production!$A$5:$A$76,B18,Production!$F$5:$F$76) | F18: =E18-D18 | G18: =F18/E18 | H18: =D18/SUMIF(Production!$A$5:$A$76,B18,Production!$C$5:$C$76) | I18: =D18/SUMIF(Production!$A$5:$A$76,B18,Production!$D$5:$D$76) | J18: =E18/(SUMIF(CostData!$A$5:$A$76,B18,CostData!$C$5:$C$76)/6) | K18: =F18/D18
A19: =RANK(F19,$F$9:$F$20) | B19: Standard Bank Helpdesk | C19: Customer Care | D19: =SUMIF(CostData!$A$5:$A$76,B19,CostData!$J$5:$J$76) | E19: =SUMIF(Production!$A$5:$A$76,B19,Production!$F$5:$F$76) | F19: =E19-D19 | G19: =F19/E19 | H19: =D19/SUMIF(Production!$A$5:$A$76,B19,Production!$C$5:$C$76) | I19: =D19/SUMIF(Production!$A$5:$A$76,B19,Production!$D$5:$D$76) | J19: =E19/(SUMIF(CostData!$A$5:$A$76,B19,CostData!$C$5:$C$76)/6) | K19: =F19/D19
A20: =RANK(F20,$F$9:$F$20) | B20: Shoprite Surveys | C20: Lead Gen | D20: =SUMIF(CostData!$A$5:$A$76,B20,CostData!$J$5:$J$76) | E20: =SUMIF(Production!$A$5:$A$76,B20,Production!$F$5:$F$76) | F20: =E20-D20 | G20: =F20/E20 | H20: =D20/SUMIF(Production!$A$5:$A$76,B20,Production!$C$5:$C$76) | I20: =D20/SUMIF(Production!$A$5:$A$76,B20,Production!$D$5:$D$76) | J20: =E20/(SUMIF(CostData!$A$5:$A$76,B20,CostData!$C$5:$C$76)/6) | K20: =F20/D20
B21: TOTAL / BLENDED | D21: =SUM(D9:D20) | E21: =SUM(E9:E20) | F21: =SUM(F9:F20) | G21: =F21/E21 | K21: =F21/D21
A24: Cost Stack — Company Total
A25: Cost Category | B25: Amount | C25: % of Cost
A26: Labour | B26: =SUM(CostData!D5:D76) | C26: =B26/CostData!$J$77
A27: Telephony | B27: =SUM(CostData!E5:E76) | C27: =B27/CostData!$J$77
A28: Technology | B28: =SUM(CostData!F5:F76) | C28: =B28/CostData!$J$77
A29: Facilities | B29: =SUM(CostData!G5:G76) | C29: =B29/CostData!$J$77
A30: Training | B30: =SUM(CostData!H5:H76) | C30: =B30/CostData!$J$77
A31: Overhead | B31: =SUM(CostData!I5:I76) | C31: =B31/CostData!$J$77

Sheet Campaigns
A1: Campaign Master — Portfolio of Client Programmes
A2: 12 active BPO campaigns feeding the cost, production and profitability model
A4: Campaign ID | B4: Campaign | C4: Client | D4: Type | E4: Launch Date | F4: Peak Agents | G4: Status
A5: CMP-01 | B5: Vodacom Upgrades | C5: Vodacom | D5: Sales | E5: =DATE(2025,4,18) | F5: 55 | G5: Active
A6: CMP-02 | B6: ABSA Collections | C6: ABSA | D6: Collections | E6: =DATE(2025,1,22) | F6: 47 | G6: Active
A7: CMP-03 | B7: MTN Retentions | C7: MTN | D7: Retentions | E7: =DATE(2025,4,10) | F7: 56 | G7: Ramp-up
A8: CMP-04 | B8: Takealot Care | C8: Takealot | D8: Customer Care | E8: =DATE(2025,4,11) | F8: 62 | G8: Ramp-up
A9: CMP-05 | B9: Telkom Tech Support | C9: Telkom | D9: Tech Support | E9: =DATE(2025,5,7) | F9: 22 | G9: Active
A10: CMP-06 | B10: Nedbank Debt Review | C10: Nedbank | D10: Collections | E10: =DATE(2025,8,25) | F10: 23 | G10: Active
A11: CMP-07 | B11: DStv Upsell | C11: MultiChoice | D11: Sales | E11: =DATE(2025,8,26) | F11: 30 | G11: Active
A12: CMP-08 | B12: Discovery Lead Gen | C12: Discovery | D12: Lead Gen | E12: =DATE(2025,7,14) | F12: 33 | G12: Active
A13: CMP-09 | B13: Cell C Winback | C13: Cell C | D13: Retentions | E13: =DATE(2025,7,15) | F13: 22 | G13: Active
A14: CMP-10 | B14: OUTsurance Sales | C14: OUTsurance | D14: Sales | E14: =DATE(2025,2,21) | F14: 31 | G14: Active
A15: CMP-11 | B15: Standard Bank Helpdesk | C15: Standard Bank | D15: Customer Care | E15: =DATE(2025,5,13) | F15: 60 | G15: Ramp-up
A16: CMP-12 | B16: Shoprite Surveys | C16: Shoprite | D16: Lead Gen | E16: =DATE(2025,7,3) | F16: 32 | G16: Ramp-up

Sheet CostData
A1: Monthly Cost Ledger by Campaign (ZAR)
A2: Fully-loaded cost stack — labour, telephony, technology, facilities, training, overhead
A4: Campaign | B4: Month | C4: FTE | D4: Labour | E4: Telephony | F4: Technology | G4: Facilities | H4: Training | I4: Overhead | J4: Total Cost
A5: Vodacom Upgrades | B5: Feb-26 | C5: 57 | D5: 1252803 | E5: 117192 | F5: 40242 | G5: 78375 | H5: 11100 | I5: 166880 | J5: =SUM(D5:I5)
A6: Vodacom Upgrades | B6: Mar-26 | C6: 54 | D6: 900666 | E6: 105786 | F6: 57672 | G6: 49086 | H6: 12587 | I6: 126755 | J6: =SUM(D6:I6)
A7: Vodacom Upgrades | B7: Apr-26 | C7: 53 | D7: 889499 | E7: 110452 | F7: 46905 | G7: 62752 | H7: 6154 | I7: 139606 | J7: =SUM(D7:I7)
A8: Vodacom Upgrades | B8: May-26 | C8: 55 | D8: 1070905 | E8: 139480 | F8: 70510 | G8: 76230 | H8: 9450 | I8: 149157 | J8: =SUM(D8:I8)
A9: Vodacom Upgrades | B9: Jun-26 | C9: 56 | D9: 1066800 | E9: 87976 | F9: 69608 | G9: 89544 | H9: 4194 | I9: 180298 | J9: =SUM(D9:I9)
A10: Vodacom Upgrades | B10: Jul-26 | C10: 52 | D10: 871624 | E10: 123656 | F10: 54808 | G10: 75244 | H10: 18492 | I10: 146647 | J10: =SUM(D10:I10)
A11: ABSA Collections | B11: Feb-26 | C11: 44 | D11: 945824 | E11: 107316 | F11: 51524 | G11: 68288 | H11: 8597 | I11: 142098 | J11: =SUM(D11:I11)
A12: ABSA Collections | B12: Mar-26 | C12: 50 | D12: 907250 | E12: 116000 | F12: 57850 | G12: 52100 | H12: 6661 | I12: 155732 | J12: =SUM(D12:I12)
A13: ABSA Collections | B13: Apr-26 | C13: 46 | D13: 886190 | E13: 90528 | F13: 35374 | G13: 44206 | H13: 21974 | I13: 119382 | J13: =SUM(D13:I13)
A14: ABSA Collections | B14: May-26 | C14: 46 | D14: 933478 | E14: 60582 | F14: 41262 | G14: 54510 | H14: 14733 | I14: 93112 | J14: =SUM(D14:I14)
A15: ABSA Collections | B15: Jun-26 | C15: 45 | D15: 834660 | E15: 96930 | F15: 40905 | G15: 60075 | H15: 7676 | I15: 115093 | J15: =SUM(D15:I15)
A16: ABSA Collections | B16: Jul-26 | C16: 50 | D16: 955700 | E16: 85000 | F16: 39850 | G16: 59350 | H16: 25407 | I16: 158027 | J16: =SUM(D16:I16)
... A76: Shoprite Surveys | B76: Jul-26 | C76: 32 | D76: 623648 | E76: 71424 | F76: 28960 | G76: 49792 | H76: 21315 | I76: 84382 | J76: =SUM(D76:I76)
A77: TOTAL | C77: =SUM(C5:C76) | D77: =SUM(D5:D76) | E77: =SUM(E5:E76) | F77: =SUM(F5:F76) | G77: =SUM(G5:G76) | H77: =SUM(H5:H76) | I77: =SUM(I5:I76) | J77: =SUM(J5:J76)

Sheet Production
A1: Monthly Production & Revenue by Campaign
A2: Volume handled, conversions and revenue billed to the client per campaign per month
A4: Campaign | B4: Month | C4: Contacts Handled | D4: Conversions/Sales | E4: Conversion % | F4: Revenue Billed
A5: Vodacom Upgrades | B5: Feb-26 | C5: 21835 | D5: 1950 | E5: =D5/C5 | F5: 999620
A6: Vodacom Upgrades | B6: Mar-26 | C6: 31515 | D6: 4066 | E6: =D6/C6 | F6: 2363570
A7: Vodacom Upgrades | B7: Apr-26 | C7: 26290 | D7: 5243 | E7: =D7/C7 | F7: 2644238
A8: Vodacom Upgrades | B8: May-26 | C8: 29920 | D8: 3300 | E8: =D8/C8 | F8: 2314584
A9: Vodacom Upgrades | B9: Jun-26 | C9: 31295 | D9: 1774 | E9: =D9/C9 | F9: 1443851
A10: Vodacom Upgrades | B10: Jul-26 | C10: 33660 | D10: 3555 | E10: =D10/C10 | F10: 1556734
A11: ABSA Collections | B11: Feb-26 | C11: 26273 | D11: 3000 | E11: =D11/C11 | F11: 1534142
A12: ABSA Collections | B12: Mar-26 | C12: 19223 | D12: 3716 | E12: =D12/C12 | F12: 1310668
A13: ABSA Collections | B13: Apr-26 | C13: 27448 | D13: 3774 | E13: =D13/C13 | F13: 1550020
A14: ABSA Collections | B14: May-26 | C14: 18471 | D14: 2043 | E14: =D14/C14 | F14: 1157293
A15: ABSA Collections | B15: Jun-26 | C15: 25004 | D15: 4095 | E15: =D15/C15 | F15: 2241736
A16: ABSA Collections | B16: Jul-26 | C16: 28717 | D16: 3081 | E16: =D16/C16 | F16: 2050089
... A76: Shoprite Surveys | B76: Jul-26 | C76: 13120 | D76: 1571 | E76: =D76/C76 | F76: 762160
A77: TOTAL | C77: =SUM(C5:C76) | D77: =SUM(D5:D76) | E77: =D77/C77 | F77: =SUM(F5:F76)
