Workbook

Sheet Attrition Analysis
A1: Attrition & Tenure Cohort Dashboard
A2: All figures live-linked to EmployeeMaster. Cohorts: 0-3 / 3-6 / 6-12 / 12+ months.
A4: Total Headcount | C4: Active | E4: Resigned | G4: Attrition Rate | I4: Early Attrition (<3m) | K4: Avg Tenure (mths)
A5: =COUNTA(EmployeeMaster!$A$5:$A$224) | C5: =COUNTIF(EmployeeMaster!$H$5:$H$224,"Active") | E5: =COUNTIF(EmployeeMaster!$H$5:$H$224,"Resigned") | G5: =COUNTIF(EmployeeMaster!$H$5:$H$224,"Resigned")/COUNTA(EmployeeMaster!$A$5:$A$224) | I5: =COUNTIFS(EmployeeMaster!$H$5:$H$224,"Resigned",EmployeeMaster!$L$5:$L$224,"0-3 months")/COUNTIF(EmployeeMaster!$H$5:$H$224,"Resigned") | K5: =AVERAGE(EmployeeMaster!$K$5:$K$224)
A8: 1 | Headcount by Tenure Cohort | H8: 4 | Attrition by Department
A9: Tenure Cohort | B9: Headcount | C9: % of Total | D9: Active | E9: Resigned | F9: Attrition % (in cohort) | H9: Department | I9: Headcount | J9: Resigned | K9: Attrition %
A10: 0-3 months | B10: =COUNTIF(EmployeeMaster!$L$5:$L$224,A10) | C10: =B10/$B$4 | D10: =COUNTIFS(EmployeeMaster!$L$5:$L$224,A10,EmployeeMaster!$H$5:$H$224,"Active") | E10: =COUNTIFS(EmployeeMaster!$L$5:$L$224,A10,EmployeeMaster!$H$5:$H$224,"Resigned") | F10: =IFERROR(E10/B10,0) | H10: Operations | I10: =COUNTIF(EmployeeMaster!$D$5:$D$224,H10) | J10: =COUNTIFS(EmployeeMaster!$D$5:$D$224,H10,EmployeeMaster!$H$5:$H$224,"Resigned") | K10: =IFERROR(J10/I10,0)
A11: 3-6 months | B11: =COUNTIF(EmployeeMaster!$L$5:$L$224,A11) | C11: =B11/$B$4 | D11: =COUNTIFS(EmployeeMaster!$L$5:$L$224,A11,EmployeeMaster!$H$5:$H$224,"Active") | E11: =COUNTIFS(EmployeeMaster!$L$5:$L$224,A11,EmployeeMaster!$H$5:$H$224,"Resigned") | F11: =IFERROR(E11/B11,0) | H11: Customer Care | I11: =COUNTIF(EmployeeMaster!$D$5:$D$224,H11) | J11: =COUNTIFS(EmployeeMaster!$D$5:$D$224,H11,EmployeeMaster!$H$5:$H$224,"Resigned") | K11: =IFERROR(J11/I11,0)
A12: 6-12 months | B12: =COUNTIF(EmployeeMaster!$L$5:$L$224,A12) | C12: =B12/$B$4 | D12: =COUNTIFS(EmployeeMaster!$L$5:$L$224,A12,EmployeeMaster!$H$5:$H$224,"Active") | E12: =COUNTIFS(EmployeeMaster!$L$5:$L$224,A12,EmployeeMaster!$H$5:$H$224,"Resigned") | F12: =IFERROR(E12/B12,0) | H12: Sales | I12: =COUNTIF(EmployeeMaster!$D$5:$D$224,H12) | J12: =COUNTIFS(EmployeeMaster!$D$5:$D$224,H12,EmployeeMaster!$H$5:$H$224,"Resigned") | K12: =IFERROR(J12/I12,0)
A13: 12+ months | B13: =COUNTIF(EmployeeMaster!$L$5:$L$224,A13) | C13: =B13/$B$4 | D13: =COUNTIFS(EmployeeMaster!$L$5:$L$224,A13,EmployeeMaster!$H$5:$H$224,"Active") | E13: =COUNTIFS(EmployeeMaster!$L$5:$L$224,A13,EmployeeMaster!$H$5:$H$224,"Resigned") | F13: =IFERROR(E13/B13,0) | H13: IT Support | I13: =COUNTIF(EmployeeMaster!$D$5:$D$224,H13) | J13: =COUNTIFS(EmployeeMaster!$D$5:$D$224,H13,EmployeeMaster!$H$5:$H$224,"Resigned") | K13: =IFERROR(J13/I13,0)
A14: TOTAL | B14: =SUM(B10:B13) | C14: =SUM(C10:C13) | D14: =SUM(D10:D13) | E14: =SUM(E10:E13) | F14: =IFERROR(E14/B14,0) | H14: Admin | I14: =COUNTIF(EmployeeMaster!$D$5:$D$224,H14) | J14: =COUNTIFS(EmployeeMaster!$D$5:$D$224,H14,EmployeeMaster!$H$5:$H$224,"Resigned") | K14: =IFERROR(J14/I14,0)
H15: Quality | I15: =COUNTIF(EmployeeMaster!$D$5:$D$224,H15) | J15: =COUNTIFS(EmployeeMaster!$D$5:$D$224,H15,EmployeeMaster!$H$5:$H$224,"Resigned") | K15: =IFERROR(J15/I15,0)
A16: 2 | Gender × Tenure Cohort (headcount, and % female within cohort) | H16: Team Leaders | I16: =COUNTIF(EmployeeMaster!$D$5:$D$224,H16) | J16: =COUNTIFS(EmployeeMaster!$D$5:$D$224,H16,EmployeeMaster!$H$5:$H$224,"Resigned") | K16: =IFERROR(J16/I16,0)
A17: Tenure Cohort | B17: Female | C17: Male | D17: Total | E17: % Female | F17: % of Females Still Active | H17: Training | I17: =COUNTIF(EmployeeMaster!$D$5:$D$224,H17) | J17: =COUNTIFS(EmployeeMaster!$D$5:$D$224,H17,EmployeeMaster!$H$5:$H$224,"Resigned") | K17: =IFERROR(J17/I17,0)
A18: 0-3 months | B18: =COUNTIFS(EmployeeMaster!$L$5:$L$224,A18,EmployeeMaster!$C$5:$C$224,"Female") | C18: =COUNTIFS(EmployeeMaster!$L$5:$L$224,A18,EmployeeMaster!$C$5:$C$224,"Male") | D18: =B18+C18 | E18: =IFERROR(B18/D18,0) | F18: =IFERROR(COUNTIFS(EmployeeMaster!$L$5:$L$224,A18,EmployeeMaster!$C$5:$C$224,"Female",EmployeeMaster!$H$5:$H$224,"Active")/B18,0)
A19: 3-6 months | B19: =COUNTIFS(EmployeeMaster!$L$5:$L$224,A19,EmployeeMaster!$C$5:$C$224,"Female") | C19: =COUNTIFS(EmployeeMaster!$L$5:$L$224,A19,EmployeeMaster!$C$5:$C$224,"Male") | D19: =B19+C19 | E19: =IFERROR(B19/D19,0) | F19: =IFERROR(COUNTIFS(EmployeeMaster!$L$5:$L$224,A19,EmployeeMaster!$C$5:$C$224,"Female",EmployeeMaster!$H$5:$H$224,"Active")/B19,0)
A20: 6-12 months | B20: =COUNTIFS(EmployeeMaster!$L$5:$L$224,A20,EmployeeMaster!$C$5:$C$224,"Female") | C20: =COUNTIFS(EmployeeMaster!$L$5:$L$224,A20,EmployeeMaster!$C$5:$C$224,"Male") | D20: =B20+C20 | E20: =IFERROR(B20/D20,0) | F20: =IFERROR(COUNTIFS(EmployeeMaster!$L$5:$L$224,A20,EmployeeMaster!$C$5:$C$224,"Female",EmployeeMaster!$H$5:$H$224,"Active")/B20,0) | H20: 5 | Attrition by Campaign
A21: 12+ months | B21: =COUNTIFS(EmployeeMaster!$L$5:$L$224,A21,EmployeeMaster!$C$5:$C$224,"Female") | C21: =COUNTIFS(EmployeeMaster!$L$5:$L$224,A21,EmployeeMaster!$C$5:$C$224,"Male") | D21: =B21+C21 | E21: =IFERROR(B21/D21,0) | F21: =IFERROR(COUNTIFS(EmployeeMaster!$L$5:$L$224,A21,EmployeeMaster!$C$5:$C$224,"Female",EmployeeMaster!$H$5:$H$224,"Active")/B21,0) | H21: Campaign | I21: Headcount | J21: Resigned | K21: Attrition %
A22: TOTAL | B22: =SUM(B18:B21) | C22: =SUM(C18:C21) | D22: =SUM(D18:D21) | E22: =IFERROR(B22/D22,0) | F22: =IFERROR(COUNTIFS(EmployeeMaster!$C$5:$C$224,"Female",EmployeeMaster!$H$5:$H$224,"Active")/COUNTIF(EmployeeMaster!$C$5:$C$224,"Female"),0) | H22: Vodacom Upgrades | I22: =COUNTIF(EmployeeMaster!$E$5:$E$224,H22) | J22: =COUNTIFS(EmployeeMaster!$E$5:$E$224,H22,EmployeeMaster!$H$5:$H$224,"Resigned") | K22: =IFERROR(J22/I22,0)
H23: ABSA Collections | I23: =COUNTIF(EmployeeMaster!$E$5:$E$224,H23) | J23: =COUNTIFS(EmployeeMaster!$E$5:$E$224,H23,EmployeeMaster!$H$5:$H$224,"Resigned") | K23: =IFERROR(J23/I23,0)
A24: 3 | Gender Snapshot | H24: MTN Retentions | I24: =COUNTIF(EmployeeMaster!$E$5:$E$224,H24) | J24: =COUNTIFS(EmployeeMaster!$E$5:$E$224,H24,EmployeeMaster!$H$5:$H$224,"Resigned") | K24: =IFERROR(J24/I24,0)
A25: Total Females | B25: =COUNTIF(EmployeeMaster!$C$5:$C$224,"Female") | H25: Takealot Care | I25: =COUNTIF(EmployeeMaster!$E$5:$E$224,H25) | J25: =COUNTIFS(EmployeeMaster!$E$5:$E$224,H25,EmployeeMaster!$H$5:$H$224,"Resigned") | K25: =IFERROR(J25/I25,0)
A26: Females Still Active | B26: =COUNTIFS(EmployeeMaster!$C$5:$C$224,"Female",EmployeeMaster!$H$5:$H$224,"Active") | H26: Telkom Tech Support | I26: =COUNTIF(EmployeeMaster!$E$5:$E$224,H26) | J26: =COUNTIFS(EmployeeMaster!$E$5:$E$224,H26,EmployeeMaster!$H$5:$H$224,"Resigned") | K26: =IFERROR(J26/I26,0)
A27: % of Workforce Female | B27: =COUNTIF(EmployeeMaster!$C$5:$C$224,"Female")/COUNTA(EmployeeMaster!$A$5:$A$224) | H27: Nedbank Debt Review | I27: =COUNTIF(EmployeeMaster!$E$5:$E$224,H27) | J27: =COUNTIFS(EmployeeMaster!$E$5:$E$224,H27,EmployeeMaster!$H$5:$H$224,"Resigned") | K27: =IFERROR(J27/I27,0)
A28: % of Females Still Employed | B28: =COUNTIFS(EmployeeMaster!$C$5:$C$224,"Female",EmployeeMaster!$H$5:$H$224,"Active")/COUNTIF(EmployeeMaster!$C$5:$C$224,"Female") | H28: DStv Upsell | I28: =COUNTIF(EmployeeMaster!$E$5:$E$224,H28) | J28: =COUNTIFS(EmployeeMaster!$E$5:$E$224,H28,EmployeeMaster!$H$5:$H$224,"Resigned") | K28: =IFERROR(J28/I28,0)
A29: Female Attrition Rate | B29: =COUNTIFS(EmployeeMaster!$C$5:$C$224,"Female",EmployeeMaster!$H$5:$H$224,"Resigned")/COUNTIF(EmployeeMaster!$C$5:$C$224,"Female") | H29: Discovery Lead Gen | I29: =COUNTIF(EmployeeMaster!$E$5:$E$224,H29) | J29: =COUNTIFS(EmployeeMaster!$E$5:$E$224,H29,EmployeeMaster!$H$5:$H$224,"Resigned") | K29: =IFERROR(J29/I29,0)
A30: Male Attrition Rate | B30: =COUNTIFS(EmployeeMaster!$C$5:$C$224,"Male",EmployeeMaster!$H$5:$H$224,"Resigned")/COUNTIF(EmployeeMaster!$C$5:$C$224,"Male") | H30: Cell C Winback | I30: =COUNTIF(EmployeeMaster!$E$5:$E$224,H30) | J30: =COUNTIFS(EmployeeMaster!$E$5:$E$224,H30,EmployeeMaster!$H$5:$H$224,"Resigned") | K30: =IFERROR(J30/I30,0)
H31: OUTsurance Sales | I31: =COUNTIF(EmployeeMaster!$E$5:$E$224,H31) | J31: =COUNTIFS(EmployeeMaster!$E$5:$E$224,H31,EmployeeMaster!$H$5:$H$224,"Resigned") | K31: =IFERROR(J31/I31,0)
A32: 6 | Monthly Resignation Trend (2026) | H32: Standard Bank Helpdesk | I32: =COUNTIF(EmployeeMaster!$E$5:$E$224,H32) | J32: =COUNTIFS(EmployeeMaster!$E$5:$E$224,H32,EmployeeMaster!$H$5:$H$224,"Resigned") | K32: =IFERROR(J32/I32,0)
A33: Month | B33: Resignations | H33: Shoprite Surveys | I33: =COUNTIF(EmployeeMaster!$E$5:$E$224,H33) | J33: =COUNTIFS(EmployeeMaster!$E$5:$E$224,H33,EmployeeMaster!$H$5:$H$224,"Resigned") | K33: =IFERROR(J33/I33,0)
A34: Jan | B34: =COUNTIFS(EmployeeMaster!$I$5:$I$224,">="&DATE(2026,1,1),EmployeeMaster!$I$5:$I$224,"<"&DATE(2026,2,1))
A35: Feb | B35: =COUNTIFS(EmployeeMaster!$I$5:$I$224,">="&DATE(2026,2,1),EmployeeMaster!$I$5:$I$224,"<"&DATE(2026,3,1))
A36: Mar | B36: =COUNTIFS(EmployeeMaster!$I$5:$I$224,">="&DATE(2026,3,1),EmployeeMaster!$I$5:$I$224,"<"&DATE(2026,4,1))
A37: Apr | B37: =COUNTIFS(EmployeeMaster!$I$5:$I$224,">="&DATE(2026,4,1),EmployeeMaster!$I$5:$I$224,"<"&DATE(2026,5,1))
A38: May | B38: =COUNTIFS(EmployeeMaster!$I$5:$I$224,">="&DATE(2026,5,1),EmployeeMaster!$I$5:$I$224,"<"&DATE(2026,6,1))
A39: Jun | B39: =COUNTIFS(EmployeeMaster!$I$5:$I$224,">="&DATE(2026,6,1),EmployeeMaster!$I$5:$I$224,"<"&DATE(2026,7,1))
A40: Jul | B40: =COUNTIFS(EmployeeMaster!$I$5:$I$224,">="&DATE(2026,7,1),EmployeeMaster!$I$5:$I$224,"<"&DATE(2026,8,1))

Sheet EmployeeMaster
A1: Employee Master — 220 Staff Across Campaigns
A2: Source for cohort attrition. Tenure & cohort columns are live formulas (recalc on open).
A4: Emp ID | B4: Employee | C4: Gender | D4: Department | E4: Campaign | F4: Location | G4: Hire Date | H4: Status | I4: Exit Date | J4: Age | K4: Tenure (mths) | L4: Tenure Cohort | M4: Monthly Salary
A5: E3001 | B5: Zodwa Nkosi | C5: Male | D5: Training | E5: DStv Upsell | F5: Pretoria | G5: 45227 | H5: Active | J5: 47 | K5: =IF(H5="Resigned",(I5-G5),(TODAY()-G5))/30.437 | L5: =IF(K5<3,"0-3 months",IF(K5<6,"3-6 months",IF(K5<12,"6-12 months","12+ months"))) | M5: 33000
A6: E3002 | B6: Keabetswe Fourie | C6: Female | D6: Quality | E6: Takealot Care | F6: Port Elizabeth | G6: 45930 | H6: Active | J6: 31 | K6: =IF(H6="Resigned",(I6-G6),(TODAY()-G6))/30.437 | L6: =IF(K6<3,"0-3 months",IF(K6<6,"3-6 months",IF(K6<12,"6-12 months","12+ months"))) | M6: 28000
A7: E3003 | B7: Ntombizodwa Govender | C7: Female | D7: Sales | E7: DStv Upsell | F7: Johannesburg | G7: 45737 | H7: Active | J7: 52 | K7: =IF(H7="Resigned",(I7-G7),(TODAY()-G7))/30.437 | L7: =IF(K7<3,"0-3 months",IF(K7<6,"3-6 months",IF(K7<12,"6-12 months","12+ months"))) | M7: 18500
A8: E3004 | B8: Sipho Meyer | C8: Male | D8: Training | E8: Discovery Lead Gen | F8: Cape Town | G8: 45225 | H8: Active | J8: 25 | K8: =IF(H8="Resigned",(I8-G8),(TODAY()-G8))/30.437 | L8: =IF(K8<3,"0-3 months",IF(K8<6,"3-6 months",IF(K8<12,"6-12 months","12+ months"))) | M8: 13500
A9: E3005 | B9: Andile Khumalo | C9: Female | D9: Operations | E9: MTN Retentions | F9: Cape Town | G9: 45949 | H9: Resigned | I9: 46075 | J9: 46 | K9: =IF(H9="Resigned",(I9-G9),(TODAY()-G9))/30.437 | L9: =IF(K9<3,"0-3 months",IF(K9<6,"3-6 months",IF(K9<12,"6-12 months","12+ months"))) | M9: 18500
A10: E3006 | B10: Nokuthula Petersen | C10: Female | D10: Quality | E10: Takealot Care | F10: Cape Town | G10: 45882 | H10: Active | J10: 41 | K10: =IF(H10="Resigned",(I10-G10),(TODAY()-G10))/30.437 | L10: =IF(K10<3,"0-3 months",IF(K10<6,"3-6 months",IF(K10<12,"6-12 months","12+ months"))) | M10: 13500
A11: E3007 | B11: Andile Tshabalala | C11: Male | D11: Team Leaders | E11: DStv Upsell | F11: Cape Town | G11: 45684 | H11: Active | J11: 34 | K11: =IF(H11="Resigned",(I11-G11),(TODAY()-G11))/30.437 | L11: =IF(K11<3,"0-3 months",IF(K11<6,"3-6 months",IF(K11<12,"6-12 months","12+ months"))) | M11: 39000
A12: E3008 | B12: Thabo Dlamini | C12: Male | D12: Quality | E12: ABSA Collections | F12: Port Elizabeth | G12: 44965 | H12: Active | J12: 43 | K12: =IF(H12="Resigned",(I12-G12),(TODAY()-G12))/30.437 | L12: =IF(K12<3,"0-3 months",IF(K12<6,"3-6 months",IF(K12<12,"6-12 months","12+ months"))) | M12: 24000
A13: E3009 | B13: Ntombizodwa Zulu | C13: Female | D13: Sales | E13: Telkom Tech Support | F13: Cape Town | G13: 45244 | H13: Active | J13: 54 | K13: =IF(H13="Resigned",(I13-G13),(TODAY()-G13))/30.437 | L13: =IF(K13<3,"0-3 months",IF(K13<6,"3-6 months",IF(K13<12,"6-12 months","12+ months"))) | M13: 16500
A14: E3010 | B14: Refilwe Radebe | C14: Male | D14: Training | E14: MTN Retentions | F14: Pretoria | G14: 45761 | H14: Active | J14: 48 | K14: =IF(H14="Resigned",(I14-G14),(TODAY()-G14))/30.437 | L14: =IF(K14<3,"0-3 months",IF(K14<6,"3-6 months",IF(K14<12,"6-12 months","12+ months"))) | M14: 16500
A15: E3011 | B15: Thabo Nel | C15: Female | D15: Customer Care | E15: Takealot Care | F15: Johannesburg | G15: 45639 | H15: Active | J15: 24 | K15: =IF(H15="Resigned",(I15-G15),(TODAY()-G15))/30.437 | L15: =IF(K15<3,"0-3 months",IF(K15<6,"3-6 months",IF(K15<12,"6-12 months","12+ months"))) | M15: 33000
A16: E3012 | B16: Zanele Sithole | C16: Female | D16: Quality | E16: Takealot Care | F16: Pretoria | G16: 45682 | H16: Active | J16: 48 | K16: =IF(H16="Resigned",(I16-G16),(TODAY()-G16))/30.437 | L16: =IF(K16<3,"0-3 months",IF(K16<6,"3-6 months",IF(K16<12,"6-12 months","12+ months"))) | M16: 13500
A17: E3013 | B17: Sibusiso Fourie | C17: Male | D17: Admin | E17: DStv Upsell | F17: Pretoria | G17: 45705 | H17: Active | J17: 30 | K17: =IF(H17="Resigned",(I17-G17),(TODAY()-G17))/30.437 | L17: =IF(K17<3,"0-3 months",IF(K17<6,"3-6 months",IF(K17<12,"6-12 months","12+ months"))) | M17: 15000
A18: E3014 | B18: Lindiwe Mokoena | C18: Female | D18: Training | E18: OUTsurance Sales | F18: Johannesburg | G18: 45367 | H18: Resigned | I18: 45819 | J18: 22 | K18: =IF(H18="Resigned",(I18-G18),(TODAY()-G18))/30.437 | L18: =IF(K18<3,"0-3 months",IF(K18<6,"3-6 months",IF(K18<12,"6-12 months","12+ months"))) | M18: 24000
A19: E3015 | B19: Boitumelo Zulu | C19: Female | D19: Team Leaders | E19: DStv Upsell | F19: Cape Town | G19: 45640 | H19: Active | J19: 34 | K19: =IF(H19="Resigned",(I19-G19),(TODAY()-G19))/30.437 | L19: =IF(K19<3,"0-3 months",IF(K19<6,"3-6 months",IF(K19<12,"6-12 months","12+ months"))) | M19: 18500
A20: E3016 | B20: Katlego Jacobs | C20: Female | D20: Training | E20: Discovery Lead Gen | F20: Cape Town | G20: 45810 | H20: Active | J20: 38 | K20: =IF(H20="Resigned",(I20-G20),(TODAY()-G20))/30.437 | L20: =IF(K20<3,"0-3 months",IF(K20<6,"3-6 months",IF(K20<12,"6-12 months","12+ months"))) | M20: 33000
A21: E3017 | B21: Sibusiso Radebe | C21: Female | D21: Customer Care | E21: OUTsurance Sales | F21: Port Elizabeth | G21: 45488 | H21: Active | J21: 45 | K21: =IF(H21="Resigned",(I21-G21),(TODAY()-G21))/30.437 | L21: =IF(K21<3,"0-3 months",IF(K21<6,"3-6 months",IF(K21<12,"6-12 months","12+ months"))) | M21: 33000
A22: E3018 | B22: Onalenna Naidoo | C22: Female | D22: IT Support | E22: Discovery Lead Gen | F22: Port Elizabeth | G22: 45848 | H22: Active | J22: 32 | K22: =IF(H22="Resigned",(I22-G22),(TODAY()-G22))/30.437 | L22: =IF(K22<3,"0-3 months",IF(K22<6,"3-6 months",IF(K22<12,"6-12 months","12+ months"))) | M22: 18500
A23: E3019 | B23: Mpho Zulu | C23: Female | D23: Quality | E23: Standard Bank Helpdesk | F23: Cape Town | G23: 45915 | H23: Active | J23: 29 | K23: =IF(H23="Resigned",(I23-G23),(TODAY()-G23))/30.437 | L23: =IF(K23<3,"0-3 months",IF(K23<6,"3-6 months",IF(K23<12,"6-12 months","12+ months"))) | M23: 33000
A24: E3020 | B24: Precious Sithole | C24: Female | D24: Operations | E24: Shoprite Surveys | F24: Cape Town | G24: 45844 | H24: Active | J24: 28 | K24: =IF(H24="Resigned",(I24-G24),(TODAY()-G24))/30.437 | L24: =IF(K24<3,"0-3 months",IF(K24<6,"3-6 months",IF(K24<12,"6-12 months","12+ months"))) | M24: 28000
A25: E3021 | B25: Musa Khumalo | C25: Female | D25: Operations | E25: Telkom Tech Support | F25: Port Elizabeth | G25: 45245 | H25: Active | J25: 23 | K25: =IF(H25="Resigned",(I25-G25),(TODAY()-G25))/30.437 | L25: =IF(K25<3,"0-3 months",IF(K25<6,"3-6 months",IF(K25<12,"6-12 months","12+ months"))) | M25: 28000
A26: E3022 | B26: Themba Mabaso | C26: Female | D26: Training | E26: Nedbank Debt Review | F26: Port Elizabeth | G26: 45027 | H26: Active | J26: 46 | K26: =IF(H26="Resigned",(I26-G26),(TODAY()-G26))/30.437 | L26: =IF(K26<3,"0-3 months",IF(K26<6,"3-6 months",IF(K26<12,"6-12 months","12+ months"))) | M26: 24000
A27: E3023 | B27: Lindiwe Tshabalala | C27: Female | D27: IT Support | E27: Telkom Tech Support | F27: Durban | G27: 45348 | H27: Active | J27: 47 | K27: =IF(H27="Resigned",(I27-G27),(TODAY()-G27))/30.437 | L27: =IF(K27<3,"0-3 months",IF(K27<6,"3-6 months",IF(K27<12,"6-12 months","12+ months"))) | M27: 18500
A28: E3024 | B28: Lindiwe Meyer | C28: Female | D28: Operations | E28: Standard Bank Helpdesk | F28: Cape Town | G28: 45686 | H28: Active | J28: 53 | K28: =IF(H28="Resigned",(I28-G28),(TODAY()-G28))/30.437 | L28: =IF(K28<3,"0-3 months",IF(K28<6,"3-6 months",IF(K28<12,"6-12 months","12+ months"))) | M28: 13500
A29: E3025 | B29: Vusi Ndlovu | C29: Female | D29: IT Support | E29: ABSA Collections | F29: Durban | G29: 45680 | H29: Active | J29: 38 | K29: =IF(H29="Resigned",(I29-G29),(TODAY()-G29))/30.437 | L29: =IF(K29<3,"0-3 months",IF(K29<6,"3-6 months",IF(K29<12,"6-12 months","12+ months"))) | M29: 18500
A30: E3026 | B30: Tebogo Mthembu | C30: Female | D30: Admin | E30: MTN Retentions | F30: Durban | G30: 45359 | H30: Active | J30: 46 | K30: =IF(H30="Resigned",(I30-G30),(TODAY()-G30))/30.437 | L30: =IF(K30<3,"0-3 months",IF(K30<6,"3-6 months",IF(K30<12,"6-12 months","12+ months"))) | M30: 28000
... A34: E3030 | B34: Siyabonga Ngcobo | C34: Female | D34: Quality | E34: Cell C Winback | F34: Cape Town | G34: 45763 | H34: Active | J34: 31 | K34: =IF(H34="Resigned",(I34-G34),(TODAY()-G34))/30.437 | L34: =IF(K34<3,"0-3 months",IF(K34<6,"3-6 months",IF(K34<12,"6-12 months","12+ months"))) | M34: 24000
A35: E3031 | B35: Nomvula Naidoo | C35: Male | D35: Training | E35: Vodacom Upgrades | F35: Cape Town | G35: 45700 | H35: Resigned | I35: 46169 | J35: 50 | K35: =IF(H35="Resigned",(I35-G35),(TODAY()-G35))/30.437 | L35: =IF(K35<3,"0-3 months",IF(K35<6,"3-6 months",IF(K35<12,"6-12 months","12+ months"))) | M35: 39000
A36: E3032 | B36: Nonhlanhla Khumalo | C36: Male | D36: Admin | E36: Standard Bank Helpdesk | F36: Johannesburg | G36: 45826 | H36: Active | J36: 40 | K36: =IF(H36="Resigned",(I36-G36),(TODAY()-G36))/30.437 | L36: =IF(K36<3,"0-3 months",IF(K36<6,"3-6 months",IF(K36<12,"6-12 months","12+ months"))) | M36: 24000
A37: E3033 | B37: Naledi Buthelezi | C37: Male | D37: IT Support | E37: Nedbank Debt Review | F37: Port Elizabeth | G37: 45715 | H37: Resigned | I37: 46206 | J37: 52 | K37: =IF(H37="Resigned",(I37-G37),(TODAY()-G37))/30.437 | L37: =IF(K37<3,"0-3 months",IF(K37<6,"3-6 months",IF(K37<12,"6-12 months","12+ months"))) | M37: 28000
A38: E3034 | B38: Bongani Mthembu | C38: Male | D38: Training | E38: MTN Retentions | F38: Durban | G38: 45574 | H38: Active | J38: 27 | K38: =IF(H38="Resigned",(I38-G38),(TODAY()-G38))/30.437 | L38: =IF(K38<3,"0-3 months",IF(K38<6,"3-6 months",IF(K38<12,"6-12 months","12+ months"))) | M38: 39000
A39: E3035 | B39: Wandile Dlamini | C39: Male | D39: Quality | E39: Vodacom Upgrades | F39: Durban | G39: 45601 | H39: Active | J39: 30 | K39: =IF(H39="Resigned",(I39-G39),(TODAY()-G39))/30.437 | L39: =IF(K39<3,"0-3 months",IF(K39<6,"3-6 months",IF(K39<12,"6-12 months","12+ months"))) | M39: 16500
A40: E3036 | B40: Mandla Mokoena | C40: Female | D40: Customer Care | E40: ABSA Collections | F40: Johannesburg | G40: 45250 | H40: Active | J40: 23 | K40: =IF(H40="Resigned",(I40-G40),(TODAY()-G40))/30.437 | L40: =IF(K40<3,"0-3 months",IF(K40<6,"3-6 months",IF(K40<12,"6-12 months","12+ months"))) | M40: 39000
A41: E3037 | B41: Siyabonga Sithole | C41: Female | D41: Team Leaders | E41: Shoprite Surveys | F41: Port Elizabeth | G41: 44892 | H41: Active | J41: 23 | K41: =IF(H41="Resigned",(I41-G41),(TODAY()-G41))/30.437 | L41: =IF(K41<3,"0-3 months",IF(K41<6,"3-6 months",IF(K41<12,"6-12 months","12+ months"))) | M41: 28000
A42: E3038 | B42: Tshepo Ndlovu | C42: Male | D42: Admin | E42: Vodacom Upgrades | F42: Pretoria | G42: 46147 | H42: Active | J42: 34 | K42: =IF(H42="Resigned",(I42-G42),(TODAY()-G42))/30.437 | L42: =IF(K42<3,"0-3 months",IF(K42<6,"3-6 months",IF(K42<12,"6-12 months","12+ months"))) | M42: 15000
A43: E3039 | B43: Kabelo Nkosi | C43: Male | D43: Sales | E43: Vodacom Upgrades | F43: Durban | G43: 45694 | H43: Active | J43: 44 | K43: =IF(H43="Resigned",(I43-G43),(TODAY()-G43))/30.437 | L43: =IF(K43<3,"0-3 months",IF(K43<6,"3-6 months",IF(K43<12,"6-12 months","12+ months"))) | M43: 39000
A44: E3040 | B44: Boitumelo Van Wyk | C44: Male | D44: IT Support | E44: OUTsurance Sales | F44: Johannesburg | G44: 45838 | H44: Active | J44: 27 | K44: =IF(H44="Resigned",(I44-G44),(TODAY()-G44))/30.437 | L44: =IF(K44<3,"0-3 months",IF(K44<6,"3-6 months",IF(K44<12,"6-12 months","12+ months"))) | M44: 21000
A45: E3041 | B45: Zinhle Meyer | C45: Female | D45: IT Support | E45: OUTsurance Sales | F45: Port Elizabeth | G45: 45833 | H45: Active | J45: 44 | K45: =IF(H45="Resigned",(I45-G45),(TODAY()-G45))/30.437 | L45: =IF(K45<3,"0-3 months",IF(K45<6,"3-6 months",IF(K45<12,"6-12 months","12+ months"))) | M45: 18500
A46: E3042 | B46: Sanele Fourie | C46: Female | D46: Sales | E46: ABSA Collections | F46: Johannesburg | G46: 45756 | H46: Active | J46: 47 | K46: =IF(H46="Resigned",(I46-G46),(TODAY()-G46))/30.437 | L46: =IF(K46<3,"0-3 months",IF(K46<6,"3-6 months",IF(K46<12,"6-12 months","12+ months"))) | M46: 39000
A47: E3043 | B47: Lerato Nkosi | C47: Male | D47: IT Support | E47: Standard Bank Helpdesk | F47: Port Elizabeth | G47: 46093 | H47: Active | J47: 43 | K47: =IF(H47="Resigned",(I47-G47),(TODAY()-G47))/30.437 | L47: =IF(K47<3,"0-3 months",IF(K47<6,"3-6 months",IF(K47<12,"6-12 months","12+ months"))) | M47: 16500
A48: E3044 | B48: Mandla Molefe | C48: Female | D48: Admin | E48: Telkom Tech Support | F48: Port Elizabeth | G48: 45607 | H48: Active | J48: 49 | K48: =IF(H48="Resigned",(I48-G48),(TODAY()-G48))/30.437 | L48: =IF(K48<3,"0-3 months",IF(K48<6,"3-6 months",IF(K48<12,"6-12 months","12+ months"))) | M48: 13500
A49: E3045 | B49: Lwazi Ngcobo | C49: Female | D49: Sales | E49: Telkom Tech Support | F49: Port Elizabeth | G49: 45980 | H49: Active | J49: 41 | K49: =IF(H49="Resigned",(I49-G49),(TODAY()-G49))/30.437 | L49: =IF(K49<3,"0-3 months",IF(K49<6,"3-6 months",IF(K49<12,"6-12 months","12+ months"))) | M49: 16500
... A56: E3052 | B56: Neo Maseko | C56: Male | D56: Sales | E56: Vodacom Upgrades | F56: Cape Town | G56: 45713 | H56: Active | J56: 47 | K56: =IF(H56="Resigned",(I56-G56),(TODAY()-G56))/30.437 | L56: =IF(K56<3,"0-3 months",IF(K56<6,"3-6 months",IF(K56<12,"6-12 months","12+ months"))) | M56: 15000
A57: E3053 | B57: Nokuthula Zulu | C57: Male | D57: Customer Care | E57: DStv Upsell | F57: Port Elizabeth | G57: 46102 | H57: Resigned | I57: 46203 | J57: 39 | K57: =IF(H57="Resigned",(I57-G57),(TODAY()-G57))/30.437 | L57: =IF(K57<3,"0-3 months",IF(K57<6,"3-6 months",IF(K57<12,"6-12 months","12+ months"))) | M57: 24000
A58: E3054 | B58: Boitumelo Mahlangu | C58: Male | D58: Admin | E58: OUTsurance Sales | F58: Pretoria | G58: 45966 | H58: Resigned | I58: 46098 | J58: 30 | K58: =IF(H58="Resigned",(I58-G58),(TODAY()-G58))/30.437 | L58: =IF(K58<3,"0-3 months",IF(K58<6,"3-6 months",IF(K58<12,"6-12 months","12+ months"))) | M58: 15000
A59: E3055 | B59: Boitumelo Petersen | C59: Male | D59: Sales | E59: OUTsurance Sales | F59: Cape Town | G59: 45801 | H59: Active | J59: 43 | K59: =IF(H59="Resigned",(I59-G59),(TODAY()-G59))/30.437 | L59: =IF(K59<3,"0-3 months",IF(K59<6,"3-6 months",IF(K59<12,"6-12 months","12+ months"))) | M59: 15000
A60: E3056 | B60: Lindiwe Mahlangu | C60: Female | D60: Quality | E60: Telkom Tech Support | F60: Durban | G60: 45969 | H60: Active | J60: 55 | K60: =IF(H60="Resigned",(I60-G60),(TODAY()-G60))/30.437 | L60: =IF(K60<3,"0-3 months",IF(K60<6,"3-6 months",IF(K60<12,"6-12 months","12+ months"))) | M60: 18500
A61: E3057 | B61: Ntombizodwa Mokoena | C61: Male | D61: Admin | E61: Vodacom Upgrades | F61: Cape Town | G61: 45110 | H61: Active | J61: 54 | K61: =IF(H61="Resigned",(I61-G61),(TODAY()-G61))/30.437 | L61: =IF(K61<3,"0-3 months",IF(K61<6,"3-6 months",IF(K61<12,"6-12 months","12+ months"))) | M61: 28000
A62: E3058 | B62: Amahle Motaung | C62: Female | D62: Team Leaders | E62: ABSA Collections | F62: Pretoria | G62: 45462 | H62: Active | J62: 54 | K62: =IF(H62="Resigned",(I62-G62),(TODAY()-G62))/30.437 | L62: =IF(K62<3,"0-3 months",IF(K62<6,"3-6 months",IF(K62<12,"6-12 months","12+ months"))) | M62: 13500
A63: E3059 | B63: Vusi Maseko | C63: Female | D63: Team Leaders | E63: Cell C Winback | F63: Durban | G63: 45898 | H63: Active | J63: 40 | K63: =IF(H63="Resigned",(I63-G63),(TODAY()-G63))/30.437 | L63: =IF(K63<3,"0-3 months",IF(K63<6,"3-6 months",IF(K63<12,"6-12 months","12+ months"))) | M63: 13500
A64: E3060 | B64: Wandile Sithole | C64: Male | D64: Admin | E64: Cell C Winback | F64: Pretoria | G64: 45524 | H64: Active | J64: 39 | K64: =IF(H64="Resigned",(I64-G64),(TODAY()-G64))/30.437 | L64: =IF(K64<3,"0-3 months",IF(K64<6,"3-6 months",IF(K64<12,"6-12 months","12+ months"))) | M64: 18500
A65: E3061 | B65: Tumelo Naidoo | C65: Male | D65: Operations | E65: Vodacom Upgrades | F65: Johannesburg | G65: 46022 | H65: Active | J65: 49 | K65: =IF(H65="Resigned",(I65-G65),(TODAY()-G65))/30.437 | L65: =IF(K65<3,"0-3 months",IF(K65<6,"3-6 months",IF(K65<12,"6-12 months","12+ months"))) | M65: 21000
A66: E3062 | B66: Tumelo Ndlovu | C66: Male | D66: Admin | E66: Takealot Care | F66: Cape Town | G66: 45190 | H66: Resigned | I66: 45667 | J66: 47 | K66: =IF(H66="Resigned",(I66-G66),(TODAY()-G66))/30.437 | L66: =IF(K66<3,"0-3 months",IF(K66<6,"3-6 months",IF(K66<12,"6-12 months","12+ months"))) | M66: 18500
A67: E3063 | B67: Mpho Sithole | C67: Male | D67: Training | E67: MTN Retentions | F67: Pretoria | G67: 46120 | H67: Active | J67: 33 | K67: =IF(H67="Resigned",(I67-G67),(TODAY()-G67))/30.437 | L67: =IF(K67<3,"0-3 months",IF(K67<6,"3-6 months",IF(K67<12,"6-12 months","12+ months"))) | M67: 18500
A68: E3064 | B68: Tumelo Buthelezi | C68: Female | D68: Operations | E68: ABSA Collections | F68: Pretoria | G68: 45205 | H68: Active | J68: 43 | K68: =IF(H68="Resigned",(I68-G68),(TODAY()-G68))/30.437 | L68: =IF(K68<3,"0-3 months",IF(K68<6,"3-6 months",IF(K68<12,"6-12 months","12+ months"))) | M68: 28000
A69: E3065 | B69: Naledi Adams | C69: Female | D69: IT Support | E69: Discovery Lead Gen | F69: Pretoria | G69: 45651 | H69: Active | J69: 39 | K69: =IF(H69="Resigned",(I69-G69),(TODAY()-G69))/30.437 | L69: =IF(K69<3,"0-3 months",IF(K69<6,"3-6 months",IF(K69<12,"6-12 months","12+ months"))) | M69: 24000
A70: E3066 | B70: Amahle Van Wyk | C70: Female | D70: Sales | E70: Vodacom Upgrades | F70: Johannesburg | G70: 45703 | H70: Active | J70: 38 | K70: =IF(H70="Resigned",(I70-G70),(TODAY()-G70))/30.437 | L70: =IF(K70<3,"0-3 months",IF(K70<6,"3-6 months",IF(K70<12,"6-12 months","12+ months"))) | M70: 13500
A71: E3067 | B71: Bandile Meyer | C71: Male | D71: Training | E71: DStv Upsell | F71: Johannesburg | G71: 46086 | H71: Active | J71: 25 | K71: =IF(H71="Resigned",(I71-G71),(TODAY()-G71))/30.437 | L71: =IF(K71<3,"0-3 months",IF(K71<6,"3-6 months",IF(K71<12,"6-12 months","12+ months"))) | M71: 18500
A72: E3068 | B72: Gift Cele | C72: Male | D72: IT Support | E72: ABSA Collections | F72: Durban | G72: 45771 | H72: Active | J72: 35 | K72: =IF(H72="Resigned",(I72-G72),(TODAY()-G72))/30.437 | L72: =IF(K72<3,"0-3 months",IF(K72<6,"3-6 months",IF(K72<12,"6-12 months","12+ months"))) | M72: 28000
A73: E3069 | B73: Andile Tshabalala | C73: Female | D73: Customer Care | E73: DStv Upsell | F73: Pretoria | G73: 45611 | H73: Active | J73: 47 | K73: =IF(H73="Resigned",(I73-G73),(TODAY()-G73))/30.437 | L73: =IF(K73<3,"0-3 months",IF(K73<6,"3-6 months",IF(K73<12,"6-12 months","12+ months"))) | M73: 16500
A74: E3070 | B74: Ayanda Molefe | C74: Female | D74: Quality | E74: MTN Retentions | F74: Durban | G74: 45622 | H74: Active | J74: 40 | K74: =IF(H74="Resigned",(I74-G74),(TODAY()-G74))/30.437 | L74: =IF(K74<3,"0-3 months",IF(K74<6,"3-6 months",IF(K74<12,"6-12 months","12+ months"))) | M74: 39000
A75: E3071 | B75: Sipho Zulu | C75: Female | D75: Admin | E75: ABSA Collections | F75: Cape Town | G75: 45753 | H75: Active | J75: 52 | K75: =IF(H75="Resigned",(I75-G75),(TODAY()-G75))/30.437 | L75: =IF(K75<3,"0-3 months",IF(K75<6,"3-6 months",IF(K75<12,"6-12 months","12+ months"))) | M75: 21000
A76: E3072 | B76: Mpho Fourie | C76: Female | D76: Operations | E76: Vodacom Upgrades | F76: Port Elizabeth | G76: 45507 | H76: Resigned | I76: 46102 | J76: 27 | K76: =IF(H76="Resigned",(I76-G76),(TODAY()-G76))/30.437 | L76: =IF(K76<3,"0-3 months",IF(K76<6,"3-6 months",IF(K76<12,"6-12 months","12+ months"))) | M76: 18500
A77: E3073 | B77: Keabetswe Pillay | C77: Female | D77: Team Leaders | E77: Discovery Lead Gen | F77: Johannesburg | G77: 45759 | H77: Active | J77: 54 | K77: =IF(H77="Resigned",(I77-G77),(TODAY()-G77))/30.437 | L77: =IF(K77<3,"0-3 months",IF(K77<6,"3-6 months",IF(K77<12,"6-12 months","12+ months"))) | M77: 16500
A78: E3074 | B78: Musa Meyer | C78: Male | D78: Admin | E78: Standard Bank Helpdesk | F78: Port Elizabeth | G78: 45878 | H78: Resigned | I78: 45924 | J78: 39 | K78: =IF(H78="Resigned",(I78-G78),(TODAY()-G78))/30.437 | L78: =IF(K78<3,"0-3 months",IF(K78<6,"3-6 months",IF(K78<12,"6-12 months","12+ months"))) | M78: 16500
A79: E3075 | B79: Anele Molefe | C79: Female | D79: Training | E79: Nedbank Debt Review | F79: Cape Town | G79: 46008 | H79: Active | J79: 20 | K79: =IF(H79="Resigned",(I79-G79),(TODAY()-G79))/30.437 | L79: =IF(K79<3,"0-3 months",IF(K79<6,"3-6 months",IF(K79<12,"6-12 months","12+ months"))) | M79: 21000
A80: E3076 | B80: Rethabile Radebe | C80: Female | D80: Training | E80: DStv Upsell | F80: Durban | G80: 45568 | H80: Active | J80: 55 | K80: =IF(H80="Resigned",(I80-G80),(TODAY()-G80))/30.437 | L80: =IF(K80<3,"0-3 months",IF(K80<6,"3-6 months",IF(K80<12,"6-12 months","12+ months"))) | M80: 21000
A81: E3077 | B81: Sipho Botha | C81: Male | D81: Sales | E81: Shoprite Surveys | F81: Durban | G81: 45860 | H81: Active | J81: 32 | K81: =IF(H81="Resigned",(I81-G81),(TODAY()-G81))/30.437 | L81: =IF(K81<3,"0-3 months",IF(K81<6,"3-6 months",IF(K81<12,"6-12 months","12+ months"))) | M81: 18500
A82: E3078 | B82: Sipho Govender | C82: Female | D82: Admin | E82: Discovery Lead Gen | F82: Pretoria | G82: 45640 | H82: Active | J82: 55 | K82: =IF(H82="Resigned",(I82-G82),(TODAY()-G82))/30.437 | L82: =IF(K82<3,"0-3 months",IF(K82<6,"3-6 months",IF(K82<12,"6-12 months","12+ months"))) | M82: 28000
A83: E3079 | B83: Amahle Motaung | C83: Female | D83: IT Support | E83: Cell C Winback | F83: Durban | G83: 45961 | H83: Active | J83: 52 | K83: =IF(H83="Resigned",(I83-G83),(TODAY()-G83))/30.437 | L83: =IF(K83<3,"0-3 months",IF(K83<6,"3-6 months",IF(K83<12,"6-12 months","12+ months"))) | M83: 28000
A84: E3080 | B84: Precious Fourie | C84: Female | D84: Sales | E84: ABSA Collections | F84: Pretoria | G84: 45575 | H84: Resigned | I84: 45966 | J84: 44 | K84: =IF(H84="Resigned",(I84-G84),(TODAY()-G84))/30.437 | L84: =IF(K84<3,"0-3 months",IF(K84<6,"3-6 months",IF(K84<12,"6-12 months","12+ months"))) | M84: 15000
A85: E3081 | B85: Ntombi Mabaso | C85: Female | D85: Sales | E85: Discovery Lead Gen | F85: Durban | G85: 45498 | H85: Resigned | I85: 45552 | J85: 46 | K85: =IF(H85="Resigned",(I85-G85),(TODAY()-G85))/30.437 | L85: =IF(K85<3,"0-3 months",IF(K85<6,"3-6 months",IF(K85<12,"6-12 months","12+ months"))) | M85: 16500
A86: E3082 | B86: Andile Radebe | C86: Female | D86: Operations | E86: DStv Upsell | F86: Johannesburg | G86: 45740 | H86: Active | J86: 41 | K86: =IF(H86="Resigned",(I86-G86),(TODAY()-G86))/30.437 | L86: =IF(K86<3,"0-3 months",IF(K86<6,"3-6 months",IF(K86<12,"6-12 months","12+ months"))) | M86: 15000
A87: E3083 | B87: Nosipho Nel | C87: Female | D87: Quality | E87: Discovery Lead Gen | F87: Port Elizabeth | G87: 45538 | H87: Active | J87: 27 | K87: =IF(H87="Resigned",(I87-G87),(TODAY()-G87))/30.437 | L87: =IF(K87<3,"0-3 months",IF(K87<6,"3-6 months",IF(K87<12,"6-12 months","12+ months"))) | M87: 33000
A88: E3084 | B88: Keabetswe Govender | C88: Male | D88: Admin | E88: Takealot Care | F88: Johannesburg | G88: 45995 | H88: Active | J88: 42 | K88: =IF(H88="Resigned",(I88-G88),(TODAY()-G88))/30.437 | L88: =IF(K88<3,"0-3 months",IF(K88<6,"3-6 months",IF(K88<12,"6-12 months","12+ months"))) | M88: 24000
A89: E3085 | B89: Tumelo Sibiya | C89: Female | D89: Customer Care | E89: Cell C Winback | F89: Cape Town | G89: 45935 | H89: Active | J89: 42 | K89: =IF(H89="Resigned",(I89-G89),(TODAY()-G89))/30.437 | L89: =IF(K89<3,"0-3 months",IF(K89<6,"3-6 months",IF(K89<12,"6-12 months","12+ months"))) | M89: 24000
A90: E3086 | B90: Ntombizodwa Dlamini | C90: Female | D90: IT Support | E90: Nedbank Debt Review | F90: Port Elizabeth | G90: 45955 | H90: Active | J90: 45 | K90: =IF(H90="Resigned",(I90-G90),(TODAY()-G90))/30.437 | L90: =IF(K90<3,"0-3 months",IF(K90<6,"3-6 months",IF(K90<12,"6-12 months","12+ months"))) | M90: 21000
A91: E3087 | B91: Katlego Ndlovu | C91: Female | D91: Admin | E91: Takealot Care | F91: Pretoria | G91: 45976 | H91: Active | J91: 31 | K91: =IF(H91="Resigned",(I91-G91),(TODAY()-G91))/30.437 | L91: =IF(K91<3,"0-3 months",IF(K91<6,"3-6 months",IF(K91<12,"6-12 months","12+ months"))) | M91: 33000
A92: E3088 | B92: Refilwe Mahlangu | C92: Female | D92: Training | E92: MTN Retentions | F92: Pretoria | G92: 46124 | H92: Resigned | I92: 46161 | J92: 45 | K92: =IF(H92="Resigned",(I92-G92),(TODAY()-G92))/30.437 | L92: =IF(K92<3,"0-3 months",IF(K92<6,"3-6 months",IF(K92<12,"6-12 months","12+ months"))) | M92: 24000
A93: E3089 | B93: Boitumelo Botha | C93: Male | D93: Admin | E93: DStv Upsell | F93: Johannesburg | G93: 45493 | H93: Active | J93: 24 | K93: =IF(H93="Resigned",(I93-G93),(TODAY()-G93))/30.437 | L93: =IF(K93<3,"0-3 months",IF(K93<6,"3-6 months",IF(K93<12,"6-12 months","12+ months"))) | M93: 39000
A94: E3090 | B94: Kabelo Maseko | C94: Female | D94: Operations | E94: Takealot Care | F94: Durban | G94: 45771 | H94: Active | J94: 34 | K94: =IF(H94="Resigned",(I94-G94),(TODAY()-G94))/30.437 | L94: =IF(K94<3,"0-3 months",IF(K94<6,"3-6 months",IF(K94<12,"6-12 months","12+ months"))) | M94: 21000
A95: E3091 | B95: Nonhlanhla Van Wyk | C95: Female | D95: Sales | E95: DStv Upsell | F95: Durban | G95: 45862 | H95: Active | J95: 30 | K95: =IF(H95="Resigned",(I95-G95),(TODAY()-G95))/30.437 | L95: =IF(K95<3,"0-3 months",IF(K95<6,"3-6 months",IF(K95<12,"6-12 months","12+ months"))) | M95: 33000
A96: E3092 | B96: Zodwa Radebe | C96: Female | D96: Customer Care | E96: Telkom Tech Support | F96: Johannesburg | G96: 45512 | H96: Active | J96: 47 | K96: =IF(H96="Resigned",(I96-G96),(TODAY()-G96))/30.437 | L96: =IF(K96<3,"0-3 months",IF(K96<6,"3-6 months",IF(K96<12,"6-12 months","12+ months"))) | M96: 21000
A97: E3093 | B97: Naledi Nkosi | C97: Male | D97: Operations | E97: MTN Retentions | F97: Port Elizabeth | G97: 45366 | H97: Resigned | I97: 45807 | J97: 39 | K97: =IF(H97="Resigned",(I97-G97),(TODAY()-G97))/30.437 | L97: =IF(K97<3,"0-3 months",IF(K97<6,"3-6 months",IF(K97<12,"6-12 months","12+ months"))) | M97: 28000
A98: E3094 | B98: Mandla Fourie | C98: Male | D98: Admin | E98: Cell C Winback | F98: Cape Town | G98: 45552 | H98: Active | J98: 33 | K98: =IF(H98="Resigned",(I98-G98),(TODAY()-G98))/30.437 | L98: =IF(K98<3,"0-3 months",IF(K98<6,"3-6 months",IF(K98<12,"6-12 months","12+ months"))) | M98: 21000
A99: E3095 | B99: Refilwe Pillay | C99: Male | D99: Customer Care | E99: Cell C Winback | F99: Durban | G99: 45907 | H99: Active | J99: 30 | K99: =IF(H99="Resigned",(I99-G99),(TODAY()-G99))/30.437 | L99: =IF(K99<3,"0-3 months",IF(K99<6,"3-6 months",IF(K99<12,"6-12 months","12+ months"))) | M99: 13500
A100: E3096 | B100: Siyabonga Buthelezi | C100: Male | D100: Operations | E100: Telkom Tech Support | F100: Port Elizabeth | G100: 45879 | H100: Active | J100: 55 | K100: =IF(H100="Resigned",(I100-G100),(TODAY()-G100))/30.437 | L100: =IF(K100<3,"0-3 months",IF(K100<6,"3-6 months",IF(K100<12,"6-12 months","12+ months"))) | M100: 33000
A101: E3097 | B101: Nokuthula Maseko | C101: Female | D101: Operations | E101: Telkom Tech Support | F101: Durban | G101: 45569 | H101: Active | J101: 24 | K101: =IF(H101="Resigned",(I101-G101),(TODAY()-G101))/30.437 | L101: =IF(K101<3,"0-3 months",IF(K101<6,"3-6 months",IF(K101<12,"6-12 months","12+ months"))) | M101: 28000
A102: E3098 | B102: Nonhlanhla Botha | C102: Female | D102: Operations | E102: Nedbank Debt Review | F102: Pretoria | G102: 45802 | H102: Active | J102: 19 | K102: =IF(H102="Resigned",(I102-G102),(TODAY()-G102))/30.437 | L102: =IF(K102<3,"0-3 months",IF(K102<6,"3-6 months",IF(K102<12,"6-12 months","12+ months"))) | M102: 28000
A103: E3099 | B103: Mandla Nkosi | C103: Female | D103: Operations | E103: MTN Retentions | F103: Pretoria | G103: 45260 | H103: Active | J103: 26 | K103: =IF(H103="Resigned",(I103-G103),(TODAY()-G103))/30.437 | L103: =IF(K103<3,"0-3 months",IF(K103<6,"3-6 months",IF(K103<12,"6-12 months","12+ months"))) | M103: 33000
A104: E3100 | B104: Kabelo Pillay | C104: Female | D104: Customer Care | E104: MTN Retentions | F104: Durban | G104: 45681 | H104: Active | J104: 29 | K104: =IF(H104="Resigned",(I104-G104),(TODAY()-G104))/30.437 | L104: =IF(K104<3,"0-3 months",IF(K104<6,"3-6 months",IF(K104<12,"6-12 months","12+ months"))) | M104: 15000
A105: E3101 | B105: Andile Molefe | C105: Male | D105: Team Leaders | E105: DStv Upsell | F105: Pretoria | G105: 45279 | H105: Active | J105: 19 | K105: =IF(H105="Resigned",(I105-G105),(TODAY()-G105))/30.437 | L105: =IF(K105<3,"0-3 months",IF(K105<6,"3-6 months",IF(K105<12,"6-12 months","12+ months"))) | M105: 15000
A106: E3102 | B106: Kabelo Fourie | C106: Female | D106: Team Leaders | E106: Cell C Winback | F106: Durban | G106: 45806 | H106: Active | J106: 39 | K106: =IF(H106="Resigned",(I106-G106),(TODAY()-G106))/30.437 | L106: =IF(K106<3,"0-3 months",IF(K106<6,"3-6 months",IF(K106<12,"6-12 months","12+ months"))) | M106: 28000
A107: E3103 | B107: Nonhlanhla Khumalo | C107: Male | D107: Admin | E107: Cell C Winback | F107: Johannesburg | G107: 45558 | H107: Active | J107: 52 | K107: =IF(H107="Resigned",(I107-G107),(TODAY()-G107))/30.437 | L107: =IF(K107<3,"0-3 months",IF(K107<6,"3-6 months",IF(K107<12,"6-12 months","12+ months"))) | M107: 16500
A108: E3104 | B108: Thabo Buthelezi | C108: Female | D108: Team Leaders | E108: ABSA Collections | F108: Pretoria | G108: 45145 | H108: Active | J108: 46 | K108: =IF(H108="Resigned",(I108-G108),(TODAY()-G108))/30.437 | L108: =IF(K108<3,"0-3 months",IF(K108<6,"3-6 months",IF(K108<12,"6-12 months","12+ months"))) | M108: 21000
A109: E3105 | B109: Amahle Adams | C109: Female | D109: Operations | E109: ABSA Collections | F109: Port Elizabeth | G109: 45049 | H109: Active | J109: 33 | K109: =IF(H109="Resigned",(I109-G109),(TODAY()-G109))/30.437 | L109: =IF(K109<3,"0-3 months",IF(K109<6,"3-6 months",IF(K109<12,"6-12 months","12+ months"))) | M109: 24000
... A112: E3108 | B112: Anele Jacobs | C112: Female | D112: Team Leaders | E112: Nedbank Debt Review | F112: Durban | G112: 45363 | H112: Active | J112: 35 | K112: =IF(H112="Resigned",(I112-G112),(TODAY()-G112))/30.437 | L112: =IF(K112<3,"0-3 months",IF(K112<6,"3-6 months",IF(K112<12,"6-12 months","12+ months"))) | M112: 15000
...
